MANIFEST.in
README.md
pyproject.toml
requirements.txt
setup.cfg
setup.py
t_pom_dentaquest/__init__.py
t_pom_dentaquest/decorators.py
t_pom_dentaquest/exceptions.py
t_pom_dentaquest/t_dentaquest.py
t_pom_dentaquest.egg-info/PKG-INFO
t_pom_dentaquest.egg-info/SOURCES.txt
t_pom_dentaquest.egg-info/dependency_links.txt
t_pom_dentaquest.egg-info/not-zip-safe
t_pom_dentaquest.egg-info/requires.txt
t_pom_dentaquest.egg-info/top_level.txt
t_pom_dentaquest/elements/__init__.py
t_pom_dentaquest/elements/container_element.py
t_pom_dentaquest/elements/select_dropdown_element.py
t_pom_dentaquest/elements/table_element.py
t_pom_dentaquest/elements/text_element.py
t_pom_dentaquest/pages/__init__.py
t_pom_dentaquest/pages/home_page.py
t_pom_dentaquest/pages/login_page.py
t_pom_dentaquest/pages/member_detail_page.py
t_pom_dentaquest/pages/member_eligibility_list_page.py
t_pom_dentaquest/pages/member_eligibility_search_page.py
t_pom_dentaquest/pages/plan_benefit_summary_page.py
tests/test_t_denta_quest.py